{
  "name": "ytLive",
  "plural": "ytLive",
  "base": "Model",
  "idInjection": true,
  "options": {
    "validateUpsert": true
  },
  "properties": {},
  "validations": [],
  "relations": {},
  "acls": [],
  "methods": {
    "syncYtLiveEvents": {
      "accepts": [],
      "returns": [],
      "description": "It syncs currently live Youtube music events with recombee & elasticsearch",
      "http": [
        {
          "path": "/syncYtLiveEvents",
          "verb": "put"
        }
      ]
    }
  }
}
